pinout/__init__.py
pinout/config.py
pinout/core.py
pinout/kicad2pinout.py
pinout/manager.py
pinout/style_tools.py
pinout/templates.py
pinout/components/__init__.py
pinout/components/annotation.py
pinout/components/integrated_circuits.py
pinout/components/layout.py
pinout/components/leaderline.py
pinout/components/legend.py
pinout/components/pinlabel.py
pinout/components/text.py
pinout/resources/config.py
pinout/resources/pinout_kicad_example.zip
pinout/resources/quick_start/data.py
pinout/resources/quick_start/hardware.png
pinout/resources/quick_start/pinout_diagram.py
pinout/resources/quick_start/styles.css
pinout/resources/quick_start/__pycache__/data.cpython-39.pyc
pinout/resources/quick_start/__pycache__/pinout_diagram.cpython-39.pyc
pinout/templates/circle.svg
pinout/templates/clippath.svg
pinout/templates/component_common.svg
pinout/templates/group.svg
pinout/templates/image.svg
pinout/templates/label.svg
pinout/templates/path.svg
pinout/templates/rect.svg
pinout/templates/style.svg
pinout/templates/stylesheet.j2
pinout/templates/svg.svg
pinout/templates/text.svg
pinout/templates/textblock.svg
pinout/templates/use.svg
pinout/templates/kicad_footprint_lib/Annotation.j2
pinout/templates/kicad_footprint_lib/Origin.j2
pinout/templates/kicad_footprint_lib/PinLabel.j2
pinout-0.0.20.dist-info/LICENSE
pinout-0.0.20.dist-info/METADATA
pinout-0.0.20.dist-info/WHEEL
pinout-0.0.20.dist-info/top_level.txt
pinout-0.0.20.dist-info/RECORD
