Metadata-Version: 2.1
Name: pinout
Version: 0.0.20
Summary: Generate graphical pinout references for electronic hardware.
Home-page: https://github.com/j0ono0/pinout
Author: John Newall
Author-email: john@johnnewall.com
License: MIT
Project-URL: Bug Tracker, https://github.com/j0ono0/pinout/issues
Platform: UNKNOWN
Classifier: Development Status :: 3 - Alpha
Classifier: Programming Language :: Python :: 3
Classifier: License :: OSI Approved :: MIT License
Classifier: Operating System :: OS Independent
Requires-Python: >=3.6
License-File: LICENSE
Requires-Dist: Jinja2
Requires-Dist: Pillow
